fastapi_ext/__init__.py
fastapi_ext/utils.py
fastapi_ext/view/__init__.py
fastapi_ext/view/_params.py
fastapi_ext/view/_routes.py
fastapi_ext/view/_utils.py
fastapi_ext/view/_view.py
fastapi_ext/view/decorators/__init__.py
fastapi_ext/view/decorators/extra.py
fastapi_ext/view/decorators/modify.py
fastapi_ext/view/decorators/types.py
fastapi_ext-0.2.4.dist-info/LICENSE
fastapi_ext-0.2.4.dist-info/WHEEL
fastapi_ext-0.2.4.dist-info/METADATA
fastapi_ext-0.2.4.dist-info/RECORD
